MANIFEST.in
README.md
VERSION
setup.py
lshknn/__init__.py
lshknn/lshknn.cpp
lshknn.egg-info/PKG-INFO
lshknn.egg-info/SOURCES.txt
lshknn.egg-info/dependency_links.txt
lshknn.egg-info/not-zip-safe
lshknn.egg-info/requires.txt
lshknn.egg-info/top_level.txt
test/test_small.py
test/test_small2.py