Metadata-Version: 1.1
Name: lshknn
Version: 0.1.2
Summary: k nearest neighbor (KNN) graphs via Pearson correlation distance and local sensitive hashing (LSH).
Home-page: https://github.com/iosonofabio/lshknn
Author: Fabio Zanini
Author-email: fabio.zanini@stanford.edu
License: MIT
Platform: UNKNOWN
Classifier: Topic :: Scientific/Engineering :: Bio-Informatics
Classifier: Intended Audience :: Developers
Classifier: Intended Audience :: Science/Research
Classifier: License :: OSI Approved :: MIT License
Classifier: Operating System :: POSIX
Classifier: Programming Language :: Python
